.gitignore
.gitmodules
Makefile
README.rst
setup.cfg
setup.py
examples/time/sleep.py
src/aevent/__init__.py
src/aevent/local.py
src/aevent/pytest_plugin.py
src/aevent.egg-info/PKG-INFO
src/aevent.egg-info/SOURCES.txt
src/aevent.egg-info/dependency_links.txt
src/aevent.egg-info/entry_points.txt
src/aevent.egg-info/not-zip-safe
src/aevent.egg-info/requires.txt
src/aevent.egg-info/top_level.txt
src/aevent/_monkey/__init__.py
src/aevent/_monkey/atexit.py
src/aevent/_monkey/os.py
src/aevent/_monkey/queue.py
src/aevent/_monkey/select.py
src/aevent/_monkey/socket.py
src/aevent/_monkey/threading.py
src/aevent/_monkey/time.py
tests/conftest.py
tests/run.sh
tests/test_basic.py
tests/test_time.py
tests/pyroute2/conftest.py
tests/pyroute2/general/conftest.py