Metadata-Version: 2.1
Name: aevent
Version: 0.1.1
Summary: Call synchronous Python from async code, without blocking
Home-page: UNKNOWN
Author: Matthias Urlichs
Author-email: matthias@urlichs.de
License: MIT
Project-URL: Source code, https://github.com/M-o-a-T/aevent
Project-URL: Issue tracker, https://github.com/M-o-a-T/aevent/issues
Platform: UNKNOWN
Classifier: Development Status :: 1 - Planning
Classifier: Intended Audience :: Developers
Classifier: License :: OSI Approved :: MIT License
Classifier: Programming Language :: Python
Classifier: Programming Language :: Python :: 3
Classifier: Programming Language :: Python :: 3.7
Classifier: Programming Language :: Python :: 3.8
Classifier: Programming Language :: Python :: 3.9
Requires-Python: >=3.7.0
Provides-Extra: doc
Provides-Extra: test
Provides-Extra: trio
